codefind/__init__.py
codefind/registry.py
codefind/version.py
codefind-0.1.6.dist-info/METADATA
codefind-0.1.6.dist-info/WHEEL
codefind-0.1.6.dist-info/RECORD
